netq/__init__.py
NETQ-0.0.1.dist-info/LICENCE.txt
NETQ-0.0.1.dist-info/METADATA
NETQ-0.0.1.dist-info/WHEEL
NETQ-0.0.1.dist-info/top_level.txt
NETQ-0.0.1.dist-info/RECORD
